{
  "experiment": "ex_04_xgb",
  "timestamp": "2026-04-18T11:55:40.205054",
  "elapsed_sec": 206.5,
  "params": {
    "objective": "reg:squarederror",
    "eval_metric": "mae",
    "booster": "gbtree",
    "n_estimators": 3000,
    "learning_rate": 0.03,
    "max_depth": 8,
    "min_child_weight": 5,
    "subsample": 0.8,
    "colsample_bytree": 0.8,
    "reg_alpha": 0.1,
    "reg_lambda": 1.0,
    "random_state": 42,
    "tree_method": "hist",
    "device": "cuda",
    "verbosity": 0,
    "n_jobs": -1,
    "n_features": 140
  },
  "final_scores": {
    "mae": 561299.5673424657,
    "rmse": 751297.009478147,
    "r2": 0.7985296920121355
  },
  "total_steps": 120,
  "notes": "COGS \u2014 MAE=465,862 RMSE=628,484 R\u00b2=0.8143\n"
}